mil/__init__.py
mil/bag_representation/__init__.py
mil/bag_representation/bag_representation.py
mil/bag_representation/mapping.py
mil/bag_representation/non_mapping.py
mil/bag_representation/tests/__init__.py
mil/bag_representation/tests/test_mapping.py
mil/bag_representation/tests/test_non_mapping.py
mil/data/__init__.py
mil/data/time_series_healthcare.py
mil/data/datasets/__init__.py
mil/data/datasets/birds_brown_creeper.py
mil/data/datasets/corel_dogs.py
mil/data/datasets/elephant.py
mil/data/datasets/loader.py
mil/data/datasets/mnist_bags.py
mil/data/datasets/musk1.py
mil/data/datasets/musk2.py
mil/data/datasets/protein.py
mil/data/datasets/ucsb_breast_cancer.py
mil/data/datasets/web_recommendation_1.py
mil/data/datasets/csv/birds_brown_creeper.csv
mil/data/datasets/csv/corel_dogs.csv
mil/data/datasets/csv/elephant.csv
mil/data/datasets/csv/musk1.csv
mil/data/datasets/csv/musk2.csv
mil/data/datasets/csv/protein.csv
mil/data/datasets/csv/ucsb_breast_cancer.csv
mil/data/datasets/csv/web_recommendation_1.csv
mil/data/datasets/tests/__init__.py
mil/data/datasets/tests/test_load_datasets.py
mil/dimensionality_reduction/__init__.py
mil/dimensionality_reduction/wrapper.py
mil/errors/__init__.py
mil/errors/custom_exceptions.py
mil/errors/custom_warnings.py
mil/metrics/__init__.py
mil/metrics/custom.py
mil/metrics/manager.py
mil/metrics/wrapper.py
mil/metrics/tests/__init__.py
mil/metrics/tests/test_custom.py
mil/metrics/tests/test_manager.py
mil/models/__init__.py
mil/models/model.py
mil/models/wrapper.py
mil/models/bag_level/__init__.py
mil/models/bag_level/deep_attention.py
mil/models/bag_level/miles.py
mil/models/bag_level/tests/__init__.py
mil/models/bag_level/tests/test_deep_attention.py
mil/models/bag_level/tests/test_miles.py
mil/models/instance_level/__init__.py
mil/models/instance_level/apr.py
mil/preprocessing/__init__.py
mil/preprocessing/standarize_lists.py
mil/preprocessing/wrapper.py
mil/trainer/__init__.py
mil/trainer/trainer.py
mil-1.0.5.dist-info/LICENSE
mil-1.0.5.dist-info/METADATA
mil-1.0.5.dist-info/WHEEL
mil-1.0.5.dist-info/top_level.txt
mil-1.0.5.dist-info/RECORD
