Metadata-Version: 2.1
Name: mil
Version: 1.0.5
Summary: Multiple instance learning package for Python
Home-page: https://github.com/rosasalberto/mil
Author: Rosas, Alberto
Author-email: alberto.rosas@upc.edu
License: UNKNOWN
Platform: UNKNOWN
Classifier: License :: OSI Approved :: MIT License
Classifier: Operating System :: OS Independent
